{"stem":"bedürf","instances":[{"docId":"ed__1798-09-26","docUri":"ed__1798-09-26.html","score":1,"contexts":[{"form":"Bedürf","weight":"1","pos":2606,"context":"...einzufin= den, und das Nöthige zu Erholung ihrer <mark>Bedürf<\/mark>= nisse längstens bis 1 Uhr Nachmittags einzureichen,...","fid":"p53"}]},{"docId":"ed__1753-07-07","docUri":"ed__1753-07-07.html","score":1,"contexts":[{"form":"Bedürf","weight":"1","pos":1534,"context":"...nächst Preßburg in Hungarn siehet man täglich viele , <mark>Bedürf<\/mark>= nussen von hier abführen , wie dann imgleichen...","fid":"p34"}]},{"docId":"ed__1766-04-09","docUri":"ed__1766-04-09.html","score":1,"contexts":[{"form":"Bedürf","weight":"1","pos":1165,"context":"...d . i . Entwürfe desjenigen , was zum <mark>Bedürf<\/mark>= fen und Nutzen des Staats contribuirt werden muß...","fid":"p36"}]},{"docId":"ed__1798-09-22","docUri":"ed__1798-09-22.html","score":1,"contexts":[{"form":"Bedürf","weight":"1","pos":3083,"context":"...einzuffin= den, und das Nöthige zu Erholung ihrer <mark>Bedürf<\/mark>= nisse längstens bis 1 Uhr Nachmittags einzureichen,...","fid":"p74"}]},{"docId":"ed__1734-07-31","docUri":"ed__1734-07-31.html","score":1,"contexts":[{"form":"bedürf","weight":"1","pos":1633,"context":"...\/ als kan ein jeder papier = negotiant oder <mark>bedürf<\/mark>= tiger sich alda anmelden \/ in der versicherung...","fid":"p49"}]},{"docId":"ed__1791-07-06","docUri":"ed__1791-07-06.html","score":1,"contexts":[{"form":"Bedürf","weight":"1","pos":3571,"context":"...sittliche Erklärungen der Sonn und Festtäglichen Evangelien nach den <mark>Bedürf<\/mark>= nissen des Landvolkes . 2 ⟨Bd⟩e . 8...","fid":"p187"}]},{"docId":"ed__1740-10-22","docUri":"ed__1740-10-22.html","score":1,"contexts":[{"form":"Bedürf","weight":"1","pos":852,"context":"...Menge in = und aus= ländischer Schiffen mit allerley <mark>Bedürf<\/mark>= nüssen erwartet wird . ","fid":"p21"}]},{"docId":"ed__1791-07-09","docUri":"ed__1791-07-09.html","score":1,"contexts":[{"form":"Bedürf","weight":"1","pos":3913,"context":"...Erklärungen der Sonn und Festtäglichen Evangelien , nach den <mark>Bedürf<\/mark>= nissen des Landvolkes . 2 Bde . 8...","fid":"p129"}]}]}