{"stem":"beförderungen","instances":[{"docId":"ed__1764-04-14","docUri":"ed__1764-04-14.html","score":1,"contexts":[{"form":"Beförderungen","weight":"1","pos":614,"context":"...Krone zu setzen , und ihm darin= nen alle <mark>Beförderungen<\/mark> zu gönnen . Der Fürst Primas haben hierauf dem...","fid":"p23"}]},{"docId":"ed__1741-03-15","docUri":"ed__1741-03-15.html","score":1,"contexts":[{"form":"Beförderungen","weight":"1","pos":98,"context":"Von denen vor einiger Zeit hier vor= gefallenen <mark>Beförderungen<\/mark> seynd noch folgende nachzuholen. Es haben nem= lich...","fid":"p4"}]},{"docId":"ed__1791-07-06","docUri":"ed__1791-07-06.html","score":1,"contexts":[{"form":"Beförderungen","weight":"1","pos":1079,"context":"...die Wege geöfnet werden , um nach Verdiensten zu <mark>Beförderungen<\/mark> zu gelangen . Was die auswärtigen An= gelegenheiten betrifft...","fid":"p44"}]},{"docId":"ed__1744-03-11","docUri":"ed__1744-03-11.html","score":1,"contexts":[{"form":"Beförderungen","weight":"1","pos":385,"context":"...Königl . Majest . haben bey Dero Armee folgende <mark>Beförderungen<\/mark> gema= chet : Der Graf = Albemarle hat...","fid":"p13"}]},{"docId":"ed__1791-12-10","docUri":"ed__1791-12-10.html","score":1,"contexts":[{"form":"Beförderungen","weight":"1","pos":468,"context":"...lichkeiten , aber ohne die sonst gewöhnli= chen <mark>Beförderungen<\/mark> , gehalten worden . ","fid":"p22"}]}]}