{"stem":"billiard","instances":[{"docId":"ed__1771-03-20","docUri":"ed__1771-03-20.html","score":1,"contexts":[{"form":"Billiard","weight":"1","pos":5014,"context":"...Lusthaus , nicht minder in zweyten Stock ein sauberes <mark>Billiard<\/mark> mit aller Zugehörde täglich zu verkaufen , oder auch...","fid":"page"}]},{"docId":"ed__1762-07-28","docUri":"ed__1762-07-28.html","score":1,"contexts":[{"form":"Billiard","weight":"1","pos":1543,"context":"...Haus=capelle, und einem darbey sich befindenden <mark>Billiard<\/mark>, nebst einem gros=sen Zier= und Baum...","fid":"page"}]}]}