{"stem":"edlbach","instances":[{"docId":"ed__1792-03-03","docUri":"ed__1792-03-03.html","score":1,"contexts":[{"form":"Edlbach","weight":"1","pos":5515,"context":"...Schlag am 13 . , dann je= ne zu <mark>Edlbach<\/mark> , Neunzen , Merkenbrechts , Wurmbach und Scheideldorf am...","fid":"page"}]},{"docId":"ed__1792-03-07","docUri":"ed__1792-03-07.html","score":1,"contexts":[{"form":"Edlbach","weight":"1","pos":4894,"context":"...Schlag am 13 . , dann je= ne zu <mark>Edlbach<\/mark> , Neunzen , Merkenbrechts , Wurmbach und Scheideldorf am...","fid":"page"}]}]}