{"stem":"exteriori","instances":[{"docId":"ed__1728-11-10","docUri":"ed__1728-11-10.html","score":1,"contexts":[{"form":"Exterioris","weight":"1","pos":2978,"context":"...Claudii , &amp; Comitatuum Varasdiensis Perpetuus Heres vend &amp; <mark>Exterioris<\/mark> Szolnolc Supremus Comes , Abbas S . Georgii Militis...","fid":"p63"}]},{"docId":"ed__1740-11-19","docUri":"ed__1740-11-19.html","score":1,"contexts":[{"form":"exteriori","weight":"1","pos":2565,"context":"...kürtzlich bekanter massen ein sowol in materia als forma <mark>exteriori<\/mark> kost= bares Werk de Originibus Juris Pontificii zum...","fid":"i82"}]}]}