{"stem":"fri","instances":[{"docId":"ed__1712-05-18","docUri":"ed__1712-05-18.html","score":7,"contexts":[{"form":"Fried","weight":"1","pos":2765,"context":"Nutrit Oliva jubar. Jm <mark>Fried<\/mark> besteht die Majestät. ","fid":"p57"},{"form":"Fried","weight":"1","pos":2839,"context":"In fulcrum pacis abundat. Soll der <mark>Fried<\/mark> im Frieden sitzen Müssen ihn die Waffen schützen....","fid":"p67"},{"form":"Fried","weight":"1","pos":3137,"context":"...GOtt wolle dem Kaiser geben Erben \/ Glük \/ <mark>Fried<\/mark> \/ langes Leben. ","fid":"p115"},{"form":"Fried","weight":"1","pos":3283,"context":"Reducis tutela quietis. Der <mark>Fried<\/mark> begabte Thron Erhält die Hungar=Kron. ","fid":"p121"},{"form":"Fried","weight":"1","pos":3324,"context":"...weit die runde Welt getheilet ist in Vier. Dan <mark>Fried<\/mark> machen ist \/ so hier aus Fürsten Götter macht...","fid":"p125"},{"form":"Fried","weight":"1","pos":3327,"context":"...ist \/ so hier aus Fürsten Götter macht \/ <mark>Fried<\/mark> machen hat bei Dir uns Ruh zuwegen bracht:...","fid":"p125"},{"form":"Fried","weight":"1","pos":3438,"context":"...Pacis Amatores ut sidera celsa micahunt. Wer den <mark>Fried<\/mark> gönnt unsern Gränzen Soll wie liechte Sterne glänzen....","fid":"p133"}]},{"docId":"ed__1789-09-16","docUri":"ed__1789-09-16.html","score":5,"contexts":[{"form":"fried","weight":"1","pos":828,"context":"...Gerüchte für ganz grundlos, ermahnen ihre guten Unterthanen <mark>fried<\/mark>= fertig bey ihren Gewerben zu bleiben, und...","fid":"p43"},{"form":"Fried","weight":"1","pos":1676,"context":"...sogenannten Sche= ren lag, um die Zufuhre nach <mark>Fried<\/mark>= richshamn zu erschweren, welchen Ort zu belagern...","fid":"p67"},{"form":"Fries","weight":"1","pos":2658,"context":"...Den 25ten Juny 1787 wurde von Seiten der Herren <mark>Fries<\/mark> und Kompagnie in Wien ein Plan öffentlich herausgegeben,...","fid":"p83"},{"form":"Fries","weight":"1","pos":2738,"context":"...finden deswegen mit Einverständniß und Bewilligung der Her= ren <mark>Fries<\/mark> und Kompagnie für gut, unser Ka= pital noch mit...","fid":"p84"},{"form":"Fries","weight":"1","pos":2757,"context":"...gemachten Bedingungen. Diese 200 Aktien sind bei Herren <mark>Fries<\/mark> und Kompagnie in Wien niedergelegt, wo man deren...","fid":"p84"}]},{"docId":"ed__1711-12-23","docUri":"ed__1711-12-23.html","score":4,"contexts":[{"form":"Fried","weight":"1","pos":3563,"context":"...die Völcker ihm treu verbleiben \/ und seine Stände <mark>Fried<\/mark> haben ; Laß Jhn Lust haben zur Lieb \/...","fid":"p90"},{"form":"Fried","weight":"1","pos":3603,"context":" Der <mark>Fried<\/mark> seye mit Euch . ","fid":"p92"},{"form":"Fried","weight":"1","pos":3774,"context":"...unter seiner Regierung gesunde Zeit im Land \/ und <mark>Fried<\/mark> in dem Königreich \/ und Hoheit und Herrlichkeit am...","fid":"p100"},{"form":"Fried","weight":"1","pos":4878,"context":"...\/ und bleibe allezeit über Euch \/ und sein <mark>Fried<\/mark> sey allzeit mit Euch . Amen . ","fid":"p122"}]},{"docId":"ed__1785-06-22","docUri":"ed__1785-06-22.html","score":3,"contexts":[{"form":"Fries","weight":"1","pos":287,"context":"...Donnerstags den 13. d. M. machte Herr Graf von <mark>Fries<\/mark> eine Lustkeise nach Kettenhof, um seinen. Nefen allda...","fid":"p13"},{"form":"Fries","weight":"1","pos":412,"context":"...tritt nun sein Sohn, der Graf Joseph von <mark>Fries<\/mark>, an seine Stelle; sonst aber wird es...","fid":"p14"},{"form":"Fried","weight":"1","pos":6672,"context":"...solchemnach werden alle und jede etwan vor= handene Hauptmann <mark>Fried<\/mark>. v. Violische Erbs= interressenten an obbestimmten Tag...","fid":"p415"}]},{"docId":"ed__1789-09-12","docUri":"ed__1789-09-12.html","score":3,"contexts":[{"form":"Fries","weight":"1","pos":2771,"context":"...25 ten Juny 1787 wurde von Seiten der Herren <mark>Fries<\/mark> und Kompagnie in Wien ein Plan öffentlich herausgegeben,...","fid":"p73"},{"form":"Fries","weight":"1","pos":2851,"context":"...finden deswegen mit Einverständniß und Bewilligung der Her= ren <mark>Fries<\/mark> und Kompagnie für ⟨gut⟩, unser Ka= pital noch mit...","fid":"p73"},{"form":"Fries","weight":"1","pos":2870,"context":"...gemachten Bedingungen. Diese 200 Aktien sind bei Herren <mark>Fries<\/mark> und Kompagnie in Wien niedergelegt, wo man deren...","fid":"p73"}]},{"docId":"ed__1791-07-06","docUri":"ed__1791-07-06.html","score":3,"contexts":[{"form":"Fried","weight":"1","pos":1903,"context":"...Jos Braunsperger , Maurer , s . K . <mark>Fried<\/mark> . alt 2 J . zu Margaret . N...","fid":"p82"},{"form":"Fried","weight":"1","pos":1928,"context":".... Kammerdien . Wit . i . S . <mark>Fried<\/mark> . alt 17 J . in der Josephst ....","fid":"p88"},{"form":"Fries","weight":"1","pos":2799,"context":"...Buchbinder in der Him= melpfortgassen , ferner bey Thomas <mark>Fries<\/mark> , Buch= binder in der Singerstrasse , dann...","fid":"p166"}]},{"docId":"ed__1720-01-10","docUri":"ed__1720-01-10.html","score":3,"contexts":[{"form":"Fried","weight":"1","pos":365,"context":"...in zwey Mona= ten die Ruh und der <mark>Fried<\/mark> erfolgen werde ; Zumalen man vernom= men \/...","fid":"p14"},{"form":"Fried","weight":"1","pos":666,"context":"...in dem Haag vermuhte \/ als dörfte baldest der <mark>Fried<\/mark> zwischen denen in der Qua= druppel = Allianz befindlich...","fid":"p18"},{"form":"Fried","weight":"1","pos":980,"context":"...den einzugehen ; Zumalen zwischen Dänemarck und Schweden der <mark>Fried<\/mark> auch schon für gewis gehalten werde ; Wie ingleichem...","fid":"p26"}]},{"docId":"ed__1714-07-11","docUri":"ed__1714-07-11.html","score":3,"contexts":[{"form":"Fried","weight":"1","pos":918,"context":"...Gevollmächtigten eingeloffen \/ mit der Zeitung \/ daß der <mark>Fried<\/mark> den 26 . Dito \/ des Nachts \/ zwischen...","fid":"p23"},{"form":"Fried","weight":"1","pos":1930,"context":"...abzusenden \/ um Jhnen Bericht zugeben \/ daß der <mark>Fried<\/mark> = und Handlschafts⟨ = ⟩ zwischen dem Herzogen...","fid":"p35"},{"form":"Fried","weight":"1","pos":1946,"context":"...\/ GOtt den Allmächtigen bittende \/ daß Er diesen <mark>Fried<\/mark> segnen \/ und solchen dem Staat und dessen Unterworffenen...","fid":"p35"}]},{"docId":"ed__1786-08-26","docUri":"ed__1786-08-26.html","score":2,"contexts":[{"form":"Fried","weight":"1","pos":1420,"context":"...= nen Beherrscher , Se . Maj . König <mark>Fried<\/mark>= rich den Zweyten , zu den Belohnungen der...","fid":"p51"},{"form":"Fried","weight":"1","pos":1479,"context":"...= riger Beherrscher , Se . Maj . König <mark>Fried<\/mark>= rich Wilhelm II . , Bruderssohn des höchstsel...","fid":"p52"}]},{"docId":"ed__1760-10-15","docUri":"ed__1760-10-15.html","score":2,"contexts":[{"form":"Fried","weight":"1","pos":1034,"context":"Hr. Ernst <mark>Fried<\/mark>. Angst, K. K. Mahler=acad.-...","fid":"p33"},{"form":"Fried","weight":"1","pos":1043,"context":"Dem <mark>Fried<\/mark>. Schneider, Schneid., s. W. Rosalia,...","fid":"p34"}]},{"docId":"ed__1780-12-09","docUri":"ed__1780-12-09.html","score":2,"contexts":[{"form":"Fried","weight":"1","pos":7069,"context":"Juglers (Joh. <mark>Fried<\/mark>.) Beyträge zur juristi= schen Biographie, oder...","fid":"i81"},{"form":"Fried","weight":"1","pos":7096,"context":"Glaser (Joh. <mark>Fried<\/mark>.) Abhandlung von den schädlichen Raupen der Obstbäume,...","fid":"i83"}]},{"docId":"ed__1780-12-02","docUri":"ed__1780-12-02.html","score":2,"contexts":[{"form":"Fried","weight":"1","pos":3745,"context":"Juglers (Joh. <mark>Fried<\/mark>) Be⟨itr⟩äge zur juristi= schen Biographie, oder...","fid":"i44"},{"form":"Fried","weight":"1","pos":3778,"context":".... 6 fl. 45 kr. ⟨G⟩laser ( Joh. <mark>Fried<\/mark>.) Abhandlung von den schädlichen Raupen der Obstbäume,...","fid":"i45"}]},{"docId":"ed__1796-06-15","docUri":"ed__1796-06-15.html","score":2,"contexts":[{"form":"Fried","weight":"1","pos":2012,"context":" <mark>Fried<\/mark> . Nikel , alt 19 J . ","fid":"i16"},{"form":"Fried","weight":"1","pos":9898,"context":"...verstorbenen Herzogl . Würtembergischen Erbmarschalls , Hrn . Baron <mark>Fried<\/mark>= rich Thumb von Neuburg zu Hammetweil , ist...","fid":"p233"}]},{"docId":"ed__1713-06-24","docUri":"ed__1713-06-24.html","score":2,"contexts":[{"form":"Fried","weight":"1","pos":355,"context":"...Divau gehalten : und darin beschlossen worden \/ den <mark>Fried<\/mark> imit Moskau welches auch den 14 . Dito ein...","fid":"p30"},{"form":"Fried","weight":"1","pos":446,"context":"...= Britannien \/ von dem 9 . reich geschlossene <mark>Fried<\/mark> \/ gleichwie in Engelland \/ also auch nunmehro in...","fid":"p41"}]},{"docId":"ed__1762-11-17","docUri":"ed__1762-11-17.html","score":2,"contexts":[{"form":"Fried","weight":"1","pos":1158,"context":"...spital=stadel auf der Landstr. s. K. <mark>Fried<\/mark>., alda, alt 5. J.","fid":"i4"},{"form":"Fried","weight":"1","pos":1185,"context":"Dem (Tit.) Hrn. <mark>Fried<\/mark>. Jgnatz Maurer, des inne= ren Stadt...","fid":"i9"}]},{"docId":"ed__1720-01-24","docUri":"ed__1720-01-24.html","score":2,"contexts":[{"form":"Fried","weight":"1","pos":756,"context":"...wan Jhre Groß = Czaarische Majestät mit Schweden in <mark>Fried<\/mark> = und Freundschaft zuleben suchen mögten ; Sonsten folge...","fid":"p31"},{"form":"Fried","weight":"1","pos":1970,"context":"...Klugheit \/ und sonderbaren Gelassenheit \/ womittels dieselbe den <mark>Fried<\/mark> dem Krieg : und die Ruhe der Unruhe vorzuziehen...","fid":"p140"}]},{"docId":"ed__1792-03-10","docUri":"ed__1792-03-10.html","score":2,"contexts":[{"form":"Fried","weight":"1","pos":4533,"context":"...gabe , in einer freyen Uebersetzung von Joh . <mark>Fried<\/mark> . Gmelin . 4 Thle . m . Kupf...","fid":"p187"},{"form":"Fried","weight":"1","pos":4608,"context":"...und Medea in Kaukasos , 2 Trauersp . von <mark>Fried<\/mark> . Max Klinger . 1 Rthl . ","fid":"p193"}]},{"docId":"ed__1753-01-17","docUri":"ed__1753-01-17.html","score":2,"contexts":[{"form":"Fried","weight":"1","pos":1589,"context":" Dem <mark>Fried<\/mark> . Eberhard , Lack . , s . K...","fid":"i13"},{"form":"Fried","weight":"1","pos":1592,"context":"...Eberhard , Lack . , s . K . <mark>Fried<\/mark> . , im kleinen Mösler = hof , alt...","fid":"i13"}]},{"docId":"ed__1751-12-18","docUri":"ed__1751-12-18.html","score":2,"contexts":[{"form":"Fried","weight":"1","pos":1452,"context":"...Cö= then , Dero Herrn Bruders , des Prinzen <mark>Fried<\/mark>= rich Erdmanns , Durchl . der General =...","fid":"p33"},{"form":"Fried","weight":"1","pos":2414,"context":" Dem <mark>Fried<\/mark> . Orrt , gew . Kais . Meister =...","fid":"i22"}]},{"docId":"ed__1747-03-25","docUri":"ed__1747-03-25.html","score":1,"contexts":[{"form":"Fried","weight":"1","pos":2627,"context":" Dem <mark>Fried<\/mark> . Meckel , Burgerl . Tischl . , s...","fid":"i30"}]},{"docId":"ed__1798-09-26","docUri":"ed__1798-09-26.html","score":1,"contexts":[{"form":"Fried","weight":"1","pos":4454,"context":"...Ch. Crollii, editio 2da auctior &amp; emendatio curante <mark>Fried<\/mark>. Ch. Exter. 4 Vol. 8. 798. 2...","fid":"p161"}]},{"docId":"ed__1776-12-18","docUri":"ed__1776-12-18.html","score":1,"contexts":[{"form":"fried","weight":"1","pos":394,"context":".... Der Katholischer Kö= nig hat dermalen Ministere von <mark>fried<\/mark>= samen Gesinnungen erwählet . Dieser Wechsel in dem...","fid":"p18"}]},{"docId":"ed__1721-05-14","docUri":"ed__1721-05-14.html","score":1,"contexts":[{"form":"Fried","weight":"1","pos":2411,"context":"...der Seelignachenden Religion fortpflanze \/ die Catholische Welt in <mark>Fried<\/mark> und Ruhe zuerhalten sich befleise =\/ auch sich ein...","fid":"p45"}]},{"docId":"ed__1749-07-30","docUri":"ed__1749-07-30.html","score":1,"contexts":[{"form":"Fried","weight":"1","pos":2115,"context":"Dem <mark>Fried<\/mark>. Breini, Bildh., s. K. Joh., bey...","fid":"i16"}]},{"docId":"ed__1715-06-22","docUri":"ed__1715-06-22.html","score":1,"contexts":[{"form":"Fried","weight":"1","pos":1534,"context":"...Anlangung im Sund bestätiget werde; Demnach \/ wan kein <mark>Fried<\/mark> erfolge solte \/ was mehrers zuberichten seyn dörfte;...","fid":"p37"}]},{"docId":"ed__1786-07-08","docUri":"ed__1786-07-08.html","score":1,"contexts":[{"form":"Fried","weight":"1","pos":5493,"context":" richtlich verordnet Johann <mark>Fried<\/mark> . Voglischen Massevertretters Hrn . Dr . Bihl in...","fid":"p223"}]},{"docId":"ed__1712-11-02","docUri":"ed__1712-11-02.html","score":1,"contexts":[{"form":"Fried","weight":"1","pos":915,"context":"...Tallard künftigen Feldzug \/ wan inzwi= schen kein <mark>Fried<\/mark> folgen solte \/ das Commando über ein Französische Ar=...","fid":"p27"}]},{"docId":"ed__1793-11-02","docUri":"ed__1793-11-02.html","score":1,"contexts":[{"form":"Fried","weight":"1","pos":1992,"context":"<mark>Fried<\/mark>. Haußer, Barbier, alt 36 J. im...","fid":"i54"}]},{"docId":"ed__1792-03-03","docUri":"ed__1792-03-03.html","score":1,"contexts":[{"form":"Fried","weight":"1","pos":1495,"context":" Dem Hrn . Jak . <mark>Fried<\/mark> . v . Fucker , Stadtmedik . in Kaschau...","fid":"i36"}]},{"docId":"ed__1707-01-01","docUri":"ed__1707-01-01.html","score":1,"contexts":[{"form":"Fried","weight":"1","pos":135,"context":"...\/ umb zu bitten \/ daß GOtt der Allmächtige <mark>Fried<\/mark> und Einigkeit denen Christlichen Fürsten ertheilen \/ auch Jhro...","fid":"p7"}]},{"docId":"ed__1792-05-19","docUri":"ed__1792-05-19.html","score":1,"contexts":[{"form":"fried","weight":"1","pos":6295,"context":"...5 ) Der allhier im Jahre 1746 gebohrne Gott= <mark>fried<\/mark> Keßler , einem Sohne des ehemaligen hie= sigen Gastwirth...","fid":"p201"}]},{"docId":"ed__1745-10-27","docUri":"ed__1745-10-27.html","score":1,"contexts":[{"form":"Fried","weight":"1","pos":3328,"context":"...heftig, und unge= „recht demselben von seinen <mark>Fried<\/mark>=brichigen „ Feinden begegnet werde. Nicht minder „...","fid":"p93"}]},{"docId":"ed__1750-07-01","docUri":"ed__1750-07-01.html","score":1,"contexts":[{"form":"Fried","weight":"1","pos":2079,"context":"Dem Hrn. <mark>Fried<\/mark>. Schuster, Ober=⟨p⟩at. im Burger=Spi= tal,...","fid":"i20"}]},{"docId":"ed__1732-07-09","docUri":"ed__1732-07-09.html","score":1,"contexts":[{"form":"Fried","weight":"1","pos":2003,"context":"Joh. <mark>Fried<\/mark>. Herbst \/ Kais. Jäger \/ in dem...","fid":"i57"}]},{"docId":"ed__1795-07-01","docUri":"ed__1795-07-01.html","score":1,"contexts":[{"form":"Fried","weight":"1","pos":2564,"context":"...Franz Schmid, gew. bg. Bierwirth, s. K. <mark>Fried<\/mark>. alt 7 J. in d. Grünangerg. N....","fid":"i7"}]},{"docId":"ed__1773-06-12","docUri":"ed__1773-06-12.html","score":1,"contexts":[{"form":"Fried","weight":"1","pos":1960,"context":"<mark>Fried<\/mark>. Klein, gem. Sold. alt 26. J....","fid":"i32"}]},{"docId":"ed__1754-08-14","docUri":"ed__1754-08-14.html","score":1,"contexts":[{"form":"Fried","weight":"1","pos":1294,"context":"Hr. <mark>Fried<\/mark>. Sartori, jubilirter Wasser=bau=aufschl.= einnehm...","fid":"i20"}]},{"docId":"ed__1781-12-29","docUri":"ed__1781-12-29.html","score":1,"contexts":[{"form":"Fried","weight":"1","pos":1860,"context":" Dem <mark>Fried<\/mark> . Heninger , bürgl . Schneiderm . s ....","fid":"p46"}]},{"docId":"ed__1759-09-22","docUri":"ed__1759-09-22.html","score":1,"contexts":[{"form":"Fried","weight":"1","pos":1391,"context":"Dem <mark>Fried<\/mark>. Gißg⟨a⟩s, Zimmerges., s. K. Anna,...","fid":"i18"}]},{"docId":"ed__1748-10-26","docUri":"ed__1748-10-26.html","score":1,"contexts":[{"form":"Fries","weight":"1","pos":571,"context":"...wieder ab= gereiset ist. Die Deputation, welche aus <mark>Fries<\/mark>= land alhier wieder angekommen, hat endlich mit...","fid":"p18"}]},{"docId":"ed__1793-02-02","docUri":"ed__1793-02-02.html","score":1,"contexts":[{"form":"Fried","weight":"1","pos":2232,"context":"<mark>Fried<\/mark>. Dirl, Mühlj. alt 48 J. alle...","fid":"i12"}]},{"docId":"ed__1742-09-19","docUri":"ed__1742-09-19.html","score":1,"contexts":[{"form":"Fried","weight":"1","pos":831,"context":"...gekommen wären \/ dem Wirt bezahlt \/ und mithin <mark>Fried<\/mark> gemacht ha= ben . Zu Miltenberg in dem Mayntzi...","fid":"p29"}]},{"docId":"ed__1713-05-24","docUri":"ed__1713-05-24.html","score":1,"contexts":[{"form":"Fried","weight":"1","pos":505,"context":"...nach En= gelland zusenden ; und \/ sobald der <mark>Fried<\/mark> seine Richtigkeit haben würde \/ sollen von den Portugesischen...","fid":"p44"}]},{"docId":"ed__1781-12-19","docUri":"ed__1781-12-19.html","score":1,"contexts":[{"form":"Fried","weight":"1","pos":4171,"context":".... und mit Erläuterungen von D . Joh . <mark>Fried<\/mark> . Karl , Grimm , erster Band , 8...","fid":"p101"}]},{"docId":"ed__1744-03-14","docUri":"ed__1744-03-14.html","score":1,"contexts":[{"form":"Fried","weight":"1","pos":1914,"context":"...= Stü= ken , Holtz = Gründen Burg = <mark>Fried<\/mark> , Kais = Ge= jaid , Fisch = Wässern...","fid":"p53"}]},{"docId":"ed__1764-04-07","docUri":"ed__1764-04-07.html","score":1,"contexts":[{"form":"Fried","weight":"1","pos":1307,"context":" Dem <mark>Fried<\/mark> . Rot , Lack , s K . Theres...","fid":"i29"}]},{"docId":"ed__1781-12-22","docUri":"ed__1781-12-22.html","score":1,"contexts":[{"form":"Fried","weight":"1","pos":2493,"context":"...allerhöchsten Befehl Sr . Majestät des Kaisers , Herr <mark>Fried<\/mark>= rich Stork , Weltpriester , und Lehrer der...","fid":"p58"}]},{"docId":"ed__1755-12-20","docUri":"ed__1755-12-20.html","score":1,"contexts":[{"form":"Fried","weight":"1","pos":741,"context":"...Leute vermutlich angreiffen dörften, wann sie das Fort <mark>Fried<\/mark>= rich erreichen wollen. ","fid":"p15"}]},{"docId":"ed__1715-07-03","docUri":"ed__1715-07-03.html","score":1,"contexts":[{"form":"Fried","weight":"1","pos":1709,"context":"...verlanget nichts mehrers \/ als mit seinen Nachbahren in <mark>Fried<\/mark> zuleben, und hat alle Willigkeit \/ die man...","fid":"p88"}]},{"docId":"ed__1747-01-07","docUri":"ed__1747-01-07.html","score":1,"contexts":[{"form":"Fried","weight":"1","pos":4276,"context":"...Waffen zu ergreifen gezwungen wäre \/ so soll kein <mark>Fried<\/mark> \/ noch Waffen = Stillstand ohne Mit = Einschliessung...","fid":"p110"}]},{"docId":"ed__1771-03-23","docUri":"ed__1771-03-23.html","score":1,"contexts":[{"form":"Fried","weight":"1","pos":403,"context":"...über die höchstbetrübte Begebenheit des tödtlichen Hintritts Königs Adolph <mark>Fried<\/mark>= rich , worauf der ganze Rath , jede...","fid":"p17"}]},{"docId":"ed__1789-07-29","docUri":"ed__1789-07-29.html","score":1,"contexts":[{"form":"Fried","weight":"1","pos":2215,"context":"Dem <mark>Fried<\/mark>. Vogt, Korporal, s. W. Mar. Anna...","fid":"i66"}]},{"docId":"ed__1789-05-23","docUri":"ed__1789-05-23.html","score":1,"contexts":[{"form":"fried","weight":"1","pos":5816,"context":"..., so die Jagdbarkeit in dasigem Langenloyser Burg= <mark>fried<\/mark> in Bestand zu nehmen gedenken, haben an besagten...","fid":"p193"}]},{"docId":"ed__1713-06-10","docUri":"ed__1713-06-10.html","score":1,"contexts":[{"form":"Fried","weight":"1","pos":805,"context":"...Brieffen \/ zu Paris den 22 . dito der <mark>Fried<\/mark> mit Engell = und Hollan Portugall \/ Praussen und...","fid":"p59"}]},{"docId":"ed__1777-08-02","docUri":"ed__1777-08-02.html","score":1,"contexts":[{"form":"Fried","weight":"1","pos":67,"context":"...hiesige Publikum ist durchgängig der Meinung , daß der <mark>Fried<\/mark> zwischen Spanien und Portugall bereits unter= zeichnet sey ....","fid":"p8"}]},{"docId":"ed__1761-11-21","docUri":"ed__1761-11-21.html","score":1,"contexts":[{"form":"Fried","weight":"1","pos":1327,"context":"...= geb . Rit . Hrn . Joh . <mark>Fried<\/mark> . Edlen v . Eger , Jhrer K ....","fid":"i23"}]},{"docId":"ed__1779-05-26","docUri":"ed__1779-05-26.html","score":1,"contexts":[{"form":"fried","weight":"1","pos":3395,"context":"...Jahr 1777 . den 13 . May dem Gott= <mark>fried<\/mark> Großfeld 1 Packel bestehend in 12 Brie= fen...","fid":"p83"}]},{"docId":"ed__1753-01-13","docUri":"ed__1753-01-13.html","score":1,"contexts":[{"form":"Fried","weight":"1","pos":1188,"context":"...darauf ward er von des Chur = fürsten , <mark>Fried<\/mark>= rich Wilhelms Truppen zum Reiter ange= worben...","fid":"p27"}]},{"docId":"ed__1791-12-10","docUri":"ed__1791-12-10.html","score":1,"contexts":[{"form":"Fries","weight":"1","pos":6245,"context":" Demnach die in causa des Handlungshau= ses <mark>Fries<\/mark> und Comp . wider Hrn . Joseph Gra= fen...","fid":"p209"}]},{"docId":"ed__1756-09-11","docUri":"ed__1756-09-11.html","score":1,"contexts":[{"form":"Fried","weight":"1","pos":946,"context":"...die den Krieg beschwerlicher macht , als vorhin der <mark>Fried<\/mark> ware ? was ist Ruhm = würdiger an der...","fid":"p21"}]},{"docId":"ed__1783-12-20","docUri":"ed__1783-12-20.html","score":1,"contexts":[{"form":"Fried","weight":"1","pos":1869,"context":" Dem <mark>Fried<\/mark> . Keilhau , Buchbind . s . W ....","fid":"i14"}]},{"docId":"ed__1703-08-08","docUri":"ed__1703-08-08.html","score":1,"contexts":[{"form":"Fried","weight":"1","pos":1050,"context":"...erwar= ten wollen \/ um so fern der <mark>Fried<\/mark> nicht bald erfolge \/ ihn mit gesambter Hand anzugreiffen...","fid":"p22"}]},{"docId":"ed__1715-07-10","docUri":"ed__1715-07-10.html","score":1,"contexts":[{"form":"Fried","weight":"1","pos":917,"context":"...die Allürte hintergangen: der Stillstand getroffen: der <mark>Fried<\/mark> geschlossen: die Handelschaft durch gewissen Tractat vernachlässiget:...","fid":"p30"}]},{"docId":"ed__1768-02-24","docUri":"ed__1768-02-24.html","score":1,"contexts":[{"form":"Fried","weight":"1","pos":5455,"context":"Logau (<mark>Fried<\/mark>. von) Sinngedichte 12. Bücher mit Anmerkungen über die...","fid":"cell163"}]},{"docId":"ed__1728-08-04","docUri":"ed__1728-08-04.html","score":1,"contexts":[{"form":"Fries","weight":"1","pos":2213,"context":"...ger Lösung deren Stücke ( ausser der Ost = <mark>Fries<\/mark>= ländischen \/ derer keine gelöset worden ) als...","fid":"p68"}]},{"docId":"ed__1796-06-04","docUri":"ed__1796-06-04.html","score":1,"contexts":[{"form":"Fried","weight":"1","pos":3470,"context":" <mark>Fried<\/mark> . Gottl . Hoog , herrs . Büchsenspanner ,...","fid":"i132"}]}]}