{"stem":"glücke","instances":[{"docId":"ed__1766-04-12","docUri":"ed__1766-04-12.html","score":3,"contexts":[{"form":"Glücke","weight":"1","pos":2237,"context":"...zur Tugend bilden , und durch beydes uns zum <mark>Glücke<\/mark> leiten . ” Dieses ist der Endzweck der Moral...","fid":"page"},{"form":"Glücke","weight":"1","pos":2347,"context":"...selige ; diese Pflichten , als Mittel zu unserm <mark>Glücke<\/mark> , sind unveränderlich , sie sind in dem ewigen...","fid":"page"},{"form":"Glücke","weight":"1","pos":2466,"context":"...den Stunden der Arbeit , und der Erholung im <mark>Glücke<\/mark> , und im Unglücke , in gesunden und kranken...","fid":"page"}]},{"docId":"ed__1775-03-18","docUri":"ed__1775-03-18.html","score":2,"contexts":[{"form":"Glücke","weight":"1","pos":2207,"context":"...Europens, und überraschte den sichern Landmann noch zum <mark>Glücke<\/mark> beym Tage. Er blähte sich auf, gos Schrecken und...","fid":"page"},{"form":"Glücke","weight":"1","pos":5887,"context":"...2 Schuh. Die übrigen Salzkammern sind zu allem <mark>Glücke<\/mark>, weil ","fid":"page"}]},{"docId":"ed__1776-12-18","docUri":"ed__1776-12-18.html","score":1,"contexts":[{"form":"Glücke","weight":"1","pos":863,"context":"...in ih= rer Flucht beschädigt worden sind . Zum <mark>Glücke<\/mark> ist die Seilspinnerey , und das Ge= bäude ,...","fid":"page"}]},{"docId":"ed__1730-03-29","docUri":"ed__1730-03-29.html","score":1,"contexts":[{"form":"Glücke","weight":"1","pos":1385,"context":".... 64931 . D . Sehet \/ wie das <mark>Glücke<\/mark> spielt . 5000 . auf N . 53130 ....","fid":"page"}]},{"docId":"ed__1773-06-09","docUri":"ed__1773-06-09.html","score":1,"contexts":[{"form":"Glücke","weight":"1","pos":721,"context":"...Waffenstillstande ihre Unter=nehmungen gegen die Türken mit vielem <mark>Glücke<\/mark> wieder angefangen, ist zwar bereits durch verschiedene Berichte...","fid":"page"}]},{"docId":"ed__1747-03-22","docUri":"ed__1747-03-22.html","score":1,"contexts":[{"form":"Glücke","weight":"1","pos":2663,"context":"...daß man der Famille dieses Generals an dem widrigen <mark>Glücke<\/mark> , welches der Vatter erfah= ren , keinen...","fid":"page"}]},{"docId":"ed__1781-12-12","docUri":"ed__1781-12-12.html","score":1,"contexts":[{"form":"Glücke","weight":"1","pos":7,"context":"...betrachte man nur , Recht alles dient zu unserm <mark>Glücke<\/mark> ; Das zeigt sich klar in der Natur Vom...","fid":"page"}]},{"docId":"ed__1768-12-10","docUri":"ed__1768-12-10.html","score":1,"contexts":[{"form":"Glücke","weight":"1","pos":2507,"context":"...den Griechen schuldig, „die sich nach dem veränderten <mark>Glücke<\/mark> ihres „Vaterlandes daselbst niederließen. Auf „den schönsten...","fid":"page"}]},{"docId":"ed__1734-07-24","docUri":"ed__1734-07-24.html","score":1,"contexts":[{"form":"glücke","weight":"1","pos":1332,"context":" seyn \/ wann ich durch meine abwesenheit euer <mark>glücke<\/mark> wieder herstellen kan . Jch verbleibe stets \/ so...","fid":"page"}]},{"docId":"ed__1789-09-12","docUri":"ed__1789-09-12.html","score":1,"contexts":[{"form":"Glücke","weight":"1","pos":1299,"context":"..., ob ich gleich noch keine Aussicht zu diesem <mark>Glücke<\/mark> vor mit habe, indem die Uneinigkeiten selbst unter den...","fid":"page"}]},{"docId":"ed__1795-07-01","docUri":"ed__1795-07-01.html","score":1,"contexts":[{"form":"glücke","weight":"1","pos":1507,"context":"...dem 13. Junius geschrieben: „Bey dem grossen Un=<mark>glücke<\/mark>, daß unsere Stadt traf, war es im=mer...","fid":"page"}]},{"docId":"ed__1729-04-09","docUri":"ed__1729-04-09.html","score":1,"contexts":[{"form":"Glücke","weight":"1","pos":76,"context":"...ihre eigene Kosten zu dienen \/ um dadurch ihr <mark>Glücke<\/mark> bey der Marine zu suchen . Es ist zwar...","fid":"page"}]},{"docId":"ed__1761-11-25","docUri":"ed__1761-11-25.html","score":1,"contexts":[{"form":"Glücke","weight":"1","pos":2181,"context":"...be= trachte es als ein meiner Bedienung zu= gekommenes <mark>Glücke<\/mark> , daß ich zum Werk= zeuge so glücklicher...","fid":"page"}]},{"docId":"ed__1781-12-29","docUri":"ed__1781-12-29.html","score":1,"contexts":[{"form":"Glücke","weight":"1","pos":939,"context":"...Meilen von Brest in den Grund sank ; zum <mark>Glücke<\/mark> wurde jedoch die Besatzun ge= rettet . Bey dieser...","fid":"page"}]},{"docId":"ed__1798-09-29","docUri":"ed__1798-09-29.html","score":1,"contexts":[{"form":"Glücke","weight":"1","pos":1750,"context":"...niemahls wirk=samer an der Erleichterung und dem <mark>Glücke<\/mark> der Völker arbeitet, als wenn man auf immer...","fid":"page"}]},{"docId":"ed__1740-11-19","docUri":"ed__1740-11-19.html","score":1,"contexts":[{"form":"Glücke","weight":"1","pos":2609,"context":"...andere \/ aber wahre Methode . Solte es das <mark>Glücke<\/mark> fügen \/ daß die fontes , wor = aus...","fid":"page"}]},{"docId":"ed__1789-05-23","docUri":"ed__1789-05-23.html","score":1,"contexts":[{"form":"Glücke","weight":"1","pos":1728,"context":"...entworfen worden ist, um den Grund zu dem dauerhaften <mark>Glücke<\/mark> dieser Repub=lik zu legen, war am 4....","fid":"page"}]},{"docId":"ed__1761-11-28","docUri":"ed__1761-11-28.html","score":1,"contexts":[{"form":"Glücke","weight":"1","pos":991,"context":"...dem Ableben des Cardinals Grafen von Serbelloni ist zum <mark>Glücke<\/mark> un= richtig befunden worden , indem Se . Emi=...","fid":"page"}]},{"docId":"ed__1791-07-13","docUri":"ed__1791-07-13.html","score":1,"contexts":[{"form":"Glücke","weight":"1","pos":1022,"context":"...alles , was mir persönlich ist , zu dem <mark>Glücke<\/mark> meines Volkes , das jederzeit der Gegenstand meiner Wünsche...","fid":"page"}]},{"docId":"ed__1776-08-21","docUri":"ed__1776-08-21.html","score":1,"contexts":[{"form":"Glücke","weight":"1","pos":2038,"context":"...gänzlich zer= schmettert zu werden , wenn nicht zum <mark>Glücke<\/mark> der Schwall nächst demselben einen tiefen Rinnsaal ausgeschwemmet hätte...","fid":"page"}]}]}