{"stem":"gramma","instances":[{"docId":"ed__1754-08-03","docUri":"ed__1754-08-03.html","score":1,"contexts":[{"form":"gramma","weight":"1","pos":2187,"context":"...générale des matiers. Oder vollständige Teutsch=Französische <mark>gramma<\/mark>- tica, mit einer neuen Syntax gferet mit...","fid":"p60"}]},{"docId":"ed__1798-10-03","docUri":"ed__1798-10-03.html","score":1,"contexts":[{"form":"Gramma","weight":"1","pos":3981,"context":"...Sprachlernen= den, um nicht ewig in den ermüdenden <mark>Gramma<\/mark>= tiken zu stecken, eine angenehme Abwechslung,...","fid":"p160"}]},{"docId":"ed__1798-09-29","docUri":"ed__1798-09-29.html","score":1,"contexts":[{"form":"Gramma","weight":"1","pos":4587,"context":"...Sprachlernen= den, um nicht ewig in den ermüdenden <mark>Gramma<\/mark>=","fid":"p223"}]},{"docId":"ed__1771-03-23","docUri":"ed__1771-03-23.html","score":1,"contexts":[{"form":"gramma","weight":"1","pos":872,"context":"...besten Schriftsteller gelehret werden , als mit den unzählich <mark>gramma<\/mark>= ticalischen Regeln , welche bisher zum größten Schaden...","fid":"p38"}]}]}