{"stem":"größte","instances":[{"docId":"ed__1789-09-16","docUri":"ed__1789-09-16.html","score":3,"contexts":[{"form":"größte","weight":"1","pos":394,"context":"...Schuppaneker Thale, ist dem Ver=nehmen nach, der <mark>größte<\/mark> Theil dersel=ben bey Cladova über die Donau ge=...","fid":"page"},{"form":"größte","weight":"1","pos":803,"context":"...entweder falschen Wer=bern in die Hände oder in <mark>größte<\/mark> Noth gerathen wären, und zum Theile sich ge=...","fid":"page"},{"form":"größte","weight":"1","pos":4190,"context":"...Verlage dieses Wer=kes, vom Anfange an bis jetzt, die <mark>größte<\/mark> Uneigennützigkeit beobachtet, ob ich gleich bey der, nach...","fid":"page"}]},{"docId":"ed__1779-05-22","docUri":"ed__1779-05-22.html","score":2,"contexts":[{"form":"größte","weight":"1","pos":42,"context":" Der König hat die <mark>größte<\/mark> Achtung für die politische Jahrgeschichte des Herrn Linquet ,...","fid":"page"},{"form":"größte","weight":"1","pos":1241,"context":"...inson= derheit für unser Etablissement , wo die <mark>größte<\/mark> Betriebsamkeit herrschet . Die vo= rige Woche kamen hier...","fid":"page"}]},{"docId":"ed__1795-07-01","docUri":"ed__1795-07-01.html","score":2,"contexts":[{"form":"größte","weight":"1","pos":740,"context":" Der <mark>größte<\/mark> Theil der Pariser Jurnale drückt sich mit Empfindung über...","fid":"page"},{"form":"größte","weight":"1","pos":871,"context":"...kündigte an, daß, da ein so wichtiges Geschäft die <mark>größte<\/mark> Reife der Berathschlagungen erfordere, der Be=richt in...","fid":"page"}]},{"docId":"ed__1780-01-01","docUri":"ed__1780-01-01.html","score":2,"contexts":[{"form":"größte","weight":"1","pos":1360,"context":"...1. am höchsten 28. Zohl 3 Lin. Den 29. <mark>größte<\/mark> Wärme + 0 12. gr. ober. Den 21....","fid":"page"},{"form":"größte","weight":"1","pos":1365,"context":"...am niedrigsten 27 Zohl 2 Lin. Den 24. 26. <mark>größte<\/mark> Kälte - 0. 1½ gr. Den 14. war Nordschein...","fid":"page"}]},{"docId":"ed__1771-03-27","docUri":"ed__1771-03-27.html","score":2,"contexts":[{"form":"größte","weight":"1","pos":575,"context":"...erste Sitzung gehalten , und die ganze Stadt das <mark>größte<\/mark> Vergnügen darüber bezeuget . ","fid":"page"},{"form":"größte","weight":"1","pos":2268,"context":"...zuwege gebracht . Die Ehre der Krone , die <mark>größte<\/mark> Angelegenheit des Staats , ist dadurch in seinem Glanz...","fid":"page"}]},{"docId":"ed__1798-09-29","docUri":"ed__1798-09-29.html","score":2,"contexts":[{"form":"größte","weight":"1","pos":1004,"context":" Jn dem Königreiche Neapel herrscht die <mark>größte<\/mark> Thätigkeit die Armee zu ver=mehren, und das...","fid":"page"},{"form":"größte","weight":"1","pos":2844,"context":"...gemalen und vergoldet werden, die noch jedermann in die <mark>größte<\/mark> Verwunderung gesezt, indem sie von Porzelain kaum zu...","fid":"page"}]},{"docId":"ed__1789-05-23","docUri":"ed__1789-05-23.html","score":2,"contexts":[{"form":"größte","weight":"1","pos":47,"context":" Der <mark>größte<\/mark> Theil der den Winter über","fid":"page"},{"form":"größte","weight":"1","pos":650,"context":"...wurde, welches aber jetzt der König thäte.\" Der <mark>größte<\/mark> Theil des Adels wollte daher die Kon=tributionen nur...","fid":"page"}]},{"docId":"ed__1780-12-06","docUri":"ed__1780-12-06.html","score":2,"contexts":[{"form":"größte","weight":"1","pos":973,"context":"...geschehene Unrecht zu erstatten; Nun aber, daß Großbrittaniens <mark>größte<\/mark> Feinde mitten in nem eigenen Busen sind, nun würde...","fid":"page"},{"form":"größte","weight":"1","pos":2960,"context":"...ihren Reiz borgen, und die Koketterie für die <mark>größte<\/mark> weibliche Vollkom=menheit halten — nein ein solcher,...","fid":"page"}]},{"docId":"ed__1785-06-29","docUri":"ed__1785-06-29.html","score":2,"contexts":[{"form":"größte","weight":"1","pos":620,"context":"...Leichen nicht mehr zählet. Ueberdieß herrscht hier die <mark>größte<\/mark> Theurung, und wir leben jetzt in den schrecklichsten...","fid":"page"},{"form":"größte","weight":"1","pos":1272,"context":"...Kai=ser sich erklärt hat, und die ohne Zwei=fel das <mark>größte<\/mark> Zutrauen verdiente, auf Seiten der Gen. Staaten noch...","fid":"page"}]},{"docId":"ed__1798-09-26","docUri":"ed__1798-09-26.html","score":1,"contexts":[{"form":"größte","weight":"1","pos":3638,"context":"...gemalen und vergoldet werden, die noch jedermann in die <mark>größte<\/mark> Bewunderung gesetzt, indem sie von Porzelain kaum zu...","fid":"page"}]},{"docId":"ed__1776-12-18","docUri":"ed__1776-12-18.html","score":1,"contexts":[{"form":"größte","weight":"1","pos":1133,"context":"...fürchterlich Geschrey , und alle Anwesende hat= ten die <mark>größte<\/mark> Mühe , ehe es ihnen gelung selbi= gen...","fid":"page"}]},{"docId":"ed__1766-03-26","docUri":"ed__1766-03-26.html","score":1,"contexts":[{"form":"größte","weight":"1","pos":3261,"context":"...= ler nicht mit Nahmen genennet , und der <mark>größte<\/mark> Theil des Publikum gieng darüber weg , es wuste...","fid":"page"}]},{"docId":"ed__1795-06-27","docUri":"ed__1795-06-27.html","score":1,"contexts":[{"form":"größte","weight":"1","pos":1503,"context":"...=brunst vom J. 1728 anrichtete, indem der <mark>größte<\/mark> Theil der damahls abgebrannten Häu=ser in Vergleich mit den...","fid":"page"}]},{"docId":"ed__1771-03-09","docUri":"ed__1771-03-09.html","score":1,"contexts":[{"form":"größte","weight":"1","pos":921,"context":"...noch nicht beruhen zu können , viel= mehr die <mark>größte<\/mark> Arbeit annoch bevorzuste= hen ; weil zwischen Vegesack...","fid":"page"}]},{"docId":"ed__1792-05-19","docUri":"ed__1792-05-19.html","score":1,"contexts":[{"form":"größte","weight":"1","pos":1451,"context":"...möglich ist . Nichts erneuern wollen , sey die <mark>größte<\/mark> Neuerung in England ; denn die Englische Konstitution sey...","fid":"page"}]},{"docId":"ed__1786-03-11","docUri":"ed__1786-03-11.html","score":1,"contexts":[{"form":"größte","weight":"1","pos":1446,"context":"...nöthigen Anstalten getroffen werden konnten. Dieser Palast ist der <mark>größte<\/mark> in der Stadt, hat einen grossen Hof und...","fid":"page"}]},{"docId":"ed__1783-09-10","docUri":"ed__1783-09-10.html","score":1,"contexts":[{"form":"größte","weight":"1","pos":4422,"context":"...dörfen . Uiberzeigt durch seine Erfahrung , daß der <mark>größte<\/mark> Theil der verderblichen Zufälle , welche diese Art von...","fid":"page"}]},{"docId":"ed__1768-03-02","docUri":"ed__1768-03-02.html","score":1,"contexts":[{"form":"größte","weight":"1","pos":1150,"context":"...Ackerbau als das einzige, oder doch als das <mark>größte<\/mark> Gut des Staats an; die andere behauptet, der...","fid":"page"}]},{"docId":"ed__1789-09-12","docUri":"ed__1789-09-12.html","score":1,"contexts":[{"form":"größte","weight":"1","pos":295,"context":" Der <mark>größte<\/mark> Theil der Zipser Gespan=schaft, besonders am...","fid":"page"}]},{"docId":"ed__1780-12-09","docUri":"ed__1780-12-09.html","score":1,"contexts":[{"form":"größte","weight":"1","pos":4450,"context":"...ihren Reiz borgen, und die Koketterie für die <mark>größte<\/mark> weibliche Vollkom=menheit halten — nein: ein solcher,...","fid":"page"}]},{"docId":"ed__1775-03-18","docUri":"ed__1775-03-18.html","score":1,"contexts":[{"form":"größte","weight":"1","pos":5957,"context":"...wie schon gemel=det worden, am dritten Tage die <mark>größte<\/mark> Höhe erreichet. ","fid":"page"}]},{"docId":"ed__1791-07-16","docUri":"ed__1791-07-16.html","score":1,"contexts":[{"form":"größte","weight":"1","pos":1142,"context":" So sehr der <mark>größte<\/mark> Theil des Reichs die neue Konstitution lobpreiset , solche...","fid":"page"}]},{"docId":"ed__1768-02-27","docUri":"ed__1768-02-27.html","score":1,"contexts":[{"form":"größte","weight":"1","pos":1466,"context":"...Doctor kaufte ohne Anstand alle Stücke an sich. Der <mark>größte<\/mark> darunter befindliche Götze ist der Radegast von einer ziemlichen...","fid":"page"}]},{"docId":"ed__1781-10-17","docUri":"ed__1781-10-17.html","score":1,"contexts":[{"form":"größte","weight":"1","pos":1074,"context":"...jenseits des Flusses San= tee ; dagegen hat der <mark>größte<\/mark> Theil un= srer Armee ihrer Stellung bey Oranje=...","fid":"page"}]},{"docId":"ed__1793-02-02","docUri":"ed__1793-02-02.html","score":1,"contexts":[{"form":"größte","weight":"1","pos":1593,"context":"...sie einzuführen gesucht hat, nichts als Unglück und das <mark>größte<\/mark> Uebel hervorgebracht hat; als wenn unter uns Menschen zu...","fid":"page"}]},{"docId":"ed__1798-10-03","docUri":"ed__1798-10-03.html","score":1,"contexts":[{"form":"größte","weight":"1","pos":2206,"context":"...aus Wid=din mit Gewißheit angeben kann, ist daß der <mark>größte<\/mark> Theil der Türkisch Kai=serlichen Armee von da abgezogen...","fid":"page"}]},{"docId":"ed__1789-09-09","docUri":"ed__1789-09-09.html","score":1,"contexts":[{"form":"größte","weight":"1","pos":3418,"context":"...Verlage dieses Wer=kes, vom Anfange an bis jetzt, die <mark>größte<\/mark> Uneigenützigkeit beobachtet, ob ich gleich bey der, nach...","fid":"page"}]},{"docId":"ed__1783-10-08","docUri":"ed__1783-10-08.html","score":1,"contexts":[{"form":"größte","weight":"1","pos":3029,"context":"...zu därfen Uiberzeigt durch seine Erfahrung , daß der <mark>größte<\/mark> Theil der verderblichen Zufälle , welche diese Art von...","fid":"page"}]},{"docId":"ed__1793-07-31","docUri":"ed__1793-07-31.html","score":1,"contexts":[{"form":"größte","weight":"1","pos":945,"context":"...Evreux, im Departemente von Eure, wo sich der <mark>größte<\/mark> Theil der angeklagten und flüchtig gewordenen Deputirten, nahment...","fid":"page"}]},{"docId":"ed__1793-10-30","docUri":"ed__1793-10-30.html","score":1,"contexts":[{"form":"größte","weight":"1","pos":9856,"context":"...= Wurmseri=schen Frey=Hussaren, das <mark>größte<\/mark> Lob beylegt. ","fid":"page"}]},{"docId":"ed__1762-11-24","docUri":"ed__1762-11-24.html","score":1,"contexts":[{"form":"größte","weight":"1","pos":482,"context":"...Gewehr, und das Volk beobach=tete die <mark>größte<\/mark> Stille, in Erwartung der würkllchen Vollziehung dieser heiligen...","fid":"page"}]},{"docId":"ed__1781-12-22","docUri":"ed__1781-12-22.html","score":1,"contexts":[{"form":"größte","weight":"1","pos":1046,"context":"...gefunden habe , die man davon hofte . Der <mark>größte<\/mark> darunter , und eben jener , worüber sich Lord...","fid":"page"}]},{"docId":"ed__1789-07-29","docUri":"ed__1789-07-29.html","score":1,"contexts":[{"form":"größte","weight":"1","pos":385,"context":"..., nach Bessarabien gezogen, und dahin auch der <mark>größte<\/mark> Theil des in der Wal=lachey gesammelten Korps aufgebrochen...","fid":"page"}]},{"docId":"ed__1792-03-10","docUri":"ed__1792-03-10.html","score":1,"contexts":[{"form":"größte","weight":"1","pos":6502,"context":"...2 Drittel , oder um die Hälfte ; der <mark>größte<\/mark> Theil aber um ein Viertel , oder ein Sechstel...","fid":"page"}]}]}