{"stem":"hocheneck","instances":[{"docId":"ed__1760-09-17","docUri":"ed__1760-09-17.html","score":1,"contexts":[{"form":"Hocheneck","weight":"1","pos":2233,"context":"...Maria Anna Gräfin von Seinsheim, geborne Freyin von <mark>Hocheneck<\/mark>. ","fid":"page"}]},{"docId":"ed__1742-09-22","docUri":"ed__1742-09-22.html","score":1,"contexts":[{"form":"Hocheneck","weight":"1","pos":1517,"context":"...Englin von und zu Wagram \/ geborne Freyin von <mark>Hocheneck<\/mark> \/ zu Wagram im Land ob der Enns ....","fid":"page"}]}]}