{"stem":"mannagettischen","instances":[{"docId":"ed__1771-03-09","docUri":"ed__1771-03-09.html","score":1,"contexts":[{"form":"Mannagettischen","weight":"1","pos":5649,"context":"..., diessertwegen am Rennwege in dem Graf Thraunisch vormals <mark>Mannagettischen<\/mark> Haus im ersten Stock sich zu melden . ","fid":"page"}]},{"docId":"ed__1722-01-03","docUri":"ed__1722-01-03.html","score":1,"contexts":[{"form":"Mannagettischen","weight":"1","pos":1880,"context":"...ein Zimmer=Gesellen sein Kind Anna \/ in <mark>Mannagettischen<\/mark> Haus am Rennweg \/ an der Hectica \/ alt...","fid":"page"}]},{"docId":"ed__1768-02-24","docUri":"ed__1768-02-24.html","score":1,"contexts":[{"form":"mannagettischen","weight":"1","pos":1931,"context":"...li=citando verkauft wird, in der Kärntnerstrasse in dem <mark>mannagettischen<\/mark> Stifthaus, oder bey dem sogenannten silbernen Becher,...","fid":"page"}]}]}