{"stem":"naturgeschicht","instances":[{"docId":"ed__1785-12-17","docUri":"ed__1785-12-17.html","score":3,"contexts":[{"form":"Naturgeschichte","weight":"1","pos":3310,"context":"Buffons <mark>Naturgeschichte<\/mark> der Vögel, aus dem Französischen mit Anmerkungen und...","fid":"p158"},{"form":"Naturgeschichte","weight":"1","pos":3408,"context":".... Leske Reise durch Sachsen, in Rücksicht der <mark>Naturgeschichte<\/mark> und Oekono= ","fid":"p165"},{"form":"Naturgeschichte","weight":"1","pos":3605,"context":"...G.) Reise durch Sachsen in Rück= sicht der <mark>Naturgeschichte<\/mark> und Oekonomie, gr4. Leipz. 785. 7 fl....","fid":"p185"}]},{"docId":"ed__1780-12-13","docUri":"ed__1780-12-13.html","score":2,"contexts":[{"form":"Naturgeschichte","weight":"1","pos":3681,"context":"Abhandlung zur <mark>Naturgeschichte<\/mark>, Physik, und Oekonomie, erster Band,...","fid":"p151"},{"form":"Naturgeschichte","weight":"1","pos":4210,"context":"— — <mark>Naturgeschichte<\/mark> der Vögel, 4 Th. m. v. K. gr....","fid":"p203"}]},{"docId":"ed__1783-09-10","docUri":"ed__1783-09-10.html","score":2,"contexts":[{"form":"Naturgeschichte","weight":"1","pos":3818,"context":".... W . K . Fr . v ) <mark>Naturgeschichte<\/mark> des Niederdeutschlandes und anderer Gegenden , nebst häufigen neuen...","fid":"p118"},{"form":"Naturgeschichte","weight":"1","pos":4251,"context":" Erxleben Anfangsgründe der <mark>Naturgeschichte<\/mark> , aufs neue heransgegeben von Gmelin , mit Kupf...","fid":"p154"}]},{"docId":"ed__1780-01-01","docUri":"ed__1780-01-01.html","score":2,"contexts":[{"form":"Naturgeschichte","weight":"1","pos":3582,"context":"Sammlungen zur Physik und <mark>Naturgeschichte<\/mark>, des 2ten Bandes erstes Stück, gr. 8....","fid":"i77"},{"form":"Naturgeschichte","weight":"1","pos":3991,"context":"Dieskau (Johann Friedr. von) <mark>Naturgeschichte<\/mark> der Nachtigall, m. K. s. Römhild 1779....","fid":"i109"}]},{"docId":"ed__1783-12-24","docUri":"ed__1783-12-24.html","score":2,"contexts":[{"form":"Naturgeschichte","weight":"1","pos":3671,"context":"...= mistische , chirurgische , dann von Gattung der <mark>Naturgeschichte<\/mark> , worunter sehr schöne vom Mi= neralreich befindlich sind...","fid":"p96"},{"form":"Naturgeschichte","weight":"1","pos":3702,"context":"...item vom Linnäus , ein Wörterbuch von der ganzen <mark>Naturgeschichte<\/mark> , wie auch von der Bo= tanik , u...","fid":"p96"}]},{"docId":"ed__1775-07-01","docUri":"ed__1775-07-01.html","score":2,"contexts":[{"form":"Naturgeschichte","weight":"1","pos":4039,"context":"..., für die Lieb= haber der Arzneywissenschaft, <mark>Naturgeschichte<\/mark>, Chimie, und Oekonomie ⁊c. erster Band,...","fid":"p202"},{"form":"Naturgeschichte","weight":"1","pos":4172,"context":"...der Ma= themathik, der vaterländischen Geschichte und der <mark>Naturgeschichte<\/mark> ⁊c. m. K. gr. 8. Prag 1775. ","fid":"p213"}]},{"docId":"ed__1783-12-20","docUri":"ed__1783-12-20.html","score":2,"contexts":[{"form":"Naturgeschichte","weight":"1","pos":4412,"context":" <mark>Naturgeschichte<\/mark> worunter sehr schöne vom Mi= neralreich befindlich sind ;...","fid":"p135"},{"form":"Naturgeschichte","weight":"1","pos":4443,"context":"...item vom Linnäus , ein Wörterbuch von der ganzen <mark>Naturgeschichte<\/mark> , wie auch von der Bo= tanik , u...","fid":"p135"}]},{"docId":"ed__1776-12-18","docUri":"ed__1776-12-18.html","score":1,"contexts":[{"form":"Naturgeschichte","weight":"1","pos":6749,"context":" Buffons ( des Herrn ) <mark>Naturgeschichte<\/mark> der Vö= gel , 4ter Band , mit Kupf...","fid":"p268"}]},{"docId":"ed__1775-06-28","docUri":"ed__1775-06-28.html","score":1,"contexts":[{"form":"Naturgeschichte","weight":"1","pos":4305,"context":"Baumers <mark>Naturgeschichte<\/mark> des Mineralreichs m. Kupf. 8. 3 fl. 20...","fid":"p198"}]},{"docId":"ed__1786-07-08","docUri":"ed__1786-07-08.html","score":1,"contexts":[{"form":"Naturgeschichte","weight":"1","pos":4804,"context":"...chy= mische und alchymistische , wie auch von der <mark>Naturgeschichte<\/mark> , samt einem gut konservirten Globus und einer Elektrisirmaschine...","fid":"p201"}]},{"docId":"ed__1773-06-09","docUri":"ed__1773-06-09.html","score":1,"contexts":[{"form":"Naturgeschichte","weight":"1","pos":3709,"context":"...nützlicher und angenehmer Gegen= stände aus allen Theilen der <mark>Naturgeschichte<\/mark>, Arzneywissenschaft und Haushältungskunst, her= ausgegeben von F....","fid":"p154"}]},{"docId":"ed__1781-12-12","docUri":"ed__1781-12-12.html","score":1,"contexts":[{"form":"Naturgeschichte","weight":"1","pos":4429,"context":"...Hüpsch ( Johann Wilhelm Karl Adolph Freyherrn von ) <mark>Naturgeschichte<\/mark> des Niederdeutschlan= des , und anderer Gegenden ,...","fid":"p149"}]},{"docId":"ed__1771-03-16","docUri":"ed__1771-03-16.html","score":1,"contexts":[{"form":"Naturgeschichte","weight":"1","pos":6602,"context":" Mineralogische Belustigungen zum Behuf der Chymie und <mark>Naturgeschichte<\/mark> des Mineralreichs , 5ter Theil . gr . 8...","fid":"p240"}]},{"docId":"ed__1771-03-20","docUri":"ed__1771-03-20.html","score":1,"contexts":[{"form":"Naturgeschichte","weight":"1","pos":6686,"context":"...Griechischen , nebst Hills Anmerkungen und einigen in die <mark>Naturgeschichte<\/mark> und Chymie einschlagenden Briefen ꝛc . 8 1770 ....","fid":"p202"}]},{"docId":"ed__1789-09-12","docUri":"ed__1789-09-12.html","score":1,"contexts":[{"form":"Naturgeschichte","weight":"1","pos":3973,"context":"...kurzverfaßter Gründe zur⟩ ⟨Pflanzenlehre, als ein zur <mark>Naturgeschichte<\/mark>⟩ ⟨unumgänglich nöthiger Theil, gr8. Wien⟩...","fid":"p178"}]},{"docId":"ed__1795-07-01","docUri":"ed__1795-07-01.html","score":1,"contexts":[{"form":"Naturgeschichte","weight":"1","pos":3667,"context":"...Beyläusig zur gleicher Zeit erscheinet ber sechste Beytrag zur <mark>Naturgeschichte<\/mark> deren Vögeln, wel= chen sich dediciren zu lassen...","fid":"p75"}]},{"docId":"ed__1780-12-09","docUri":"ed__1780-12-09.html","score":1,"contexts":[{"form":"Naturgeschichte","weight":"1","pos":6817,"context":"— —<mark>Naturgeschichte<\/mark> der Vögel, 4 Th. m. v. K. gr....","fid":"i63"}]},{"docId":"ed__1775-03-18","docUri":"ed__1775-03-18.html","score":1,"contexts":[{"form":"Naturgeschichte","weight":"1","pos":4214,"context":"Bankrofrs E. <mark>Naturgeschichte<\/mark> von Guiana in Südamerica, gr. 8. 54 kr....","fid":"p233"}]},{"docId":"ed__1792-03-07","docUri":"ed__1792-03-07.html","score":1,"contexts":[{"form":"Naturgeschichte","weight":"1","pos":8609,"context":" Unterhaltungen aus der Naturlehre und <mark>Naturgeschichte<\/mark> für die Jugend , broschirt 18 kr . ","fid":"p276"}]},{"docId":"ed__1781-10-17","docUri":"ed__1781-10-17.html","score":1,"contexts":[{"form":"Naturgeschichte","weight":"1","pos":4359,"context":" <mark>Naturgeschichte<\/mark> für Kinder von Georg Chri= stian Raff ,...","fid":"p132"}]},{"docId":"ed__1789-09-09","docUri":"ed__1789-09-09.html","score":1,"contexts":[{"form":"Naturgeschichte","weight":"1","pos":3922,"context":"...v.) kurzverfaßte Gründe zur Pflanzenlehre, als ein zur <mark>Naturgeschichte<\/mark> unumgänglich nöthiger Theil, gr8 Wien 785. 39 kr....","fid":"p154"}]},{"docId":"ed__1789-09-16","docUri":"ed__1789-09-16.html","score":1,"contexts":[{"form":"Naturgeschichte","weight":"1","pos":3359,"context":".... I. Cobres Deliciæ, oder vollkommene Sammlung zur <mark>Naturgeschichte<\/mark>, Augsburg 1782. ges. 5 fl.","fid":"p107"}]},{"docId":"ed__1783-10-08","docUri":"ed__1783-10-08.html","score":1,"contexts":[{"form":"Naturgeschichte","weight":"1","pos":3987,"context":" Büffons ( Herrn von ) <mark>Naturgeschichte<\/mark> der vier= füßigen Thiere , 7ter und 8ter Band...","fid":"p113"}]},{"docId":"ed__1775-07-05","docUri":"ed__1775-07-05.html","score":1,"contexts":[{"form":"Naturgeschichte","weight":"1","pos":6422,"context":"...Preußische Samler liefert Auszüge aus Schriften zur känntniß der <mark>Naturgeschichte<\/mark>, z⟨ur⟩ beßerung der Land= und Stadtwirthschaf,...","fid":"p318"}]},{"docId":"ed__1781-12-22","docUri":"ed__1781-12-22.html","score":1,"contexts":[{"form":"Naturgeschichte","weight":"1","pos":4271,"context":"...durch die Alpen , nebst einem Versuche über die <mark>Naturgeschichte<\/mark> der Gegend von Genf , m . K ....","fid":"p113"}]},{"docId":"ed__1777-08-02","docUri":"ed__1777-08-02.html","score":1,"contexts":[{"form":"Naturgeschichte","weight":"1","pos":4140,"context":" Buffon ( des Herrn von ) allgemeine <mark>Naturgeschichte<\/mark> , eine freye mit einigen Zusätzen , Anmer=...","fid":"p118"}]},{"docId":"ed__1766-04-05","docUri":"ed__1766-04-05.html","score":1,"contexts":[{"form":"Naturgeschichte","weight":"1","pos":762,"context":"...die Ehre gehabt Jhro Majestät den 14ten Theil seiner <mark>Naturgeschichte<\/mark> zu über= reichen . Bey Ankündung der Fasten für...","fid":"p26"}]},{"docId":"ed__1792-03-10","docUri":"ed__1792-03-10.html","score":1,"contexts":[{"form":"Naturgeschichte","weight":"1","pos":4551,"context":"..., das alle Benen= nungen der Kunstwörter der <mark>Naturgeschichte<\/mark> nach ihrem ganzen Umfang erklärt . 7 Bde ....","fid":"p188"}]},{"docId":"ed__1777-06-07","docUri":"ed__1777-06-07.html","score":1,"contexts":[{"form":"Naturgeschichte","weight":"1","pos":4081,"context":"...Onomatologia historiæ naturalis , oder vollständiges Le= xikon der <mark>Naturgeschichte<\/mark> , 6 Theile , 8 . Ulm 1758 —...","fid":"i105"}]}]}