{"stem":"sauerkräutl","instances":[{"docId":"ed__1764-04-07","docUri":"ed__1764-04-07.html","score":2,"contexts":[{"form":"Sauerkräutlers","weight":"1","pos":1981,"context":"...weil . Christoph Miller , gewest = Burgerl . <mark>Sauerkräutlers<\/mark> seel . hinterlassener Sauer= kräutler = handel ,...","fid":"page"},{"form":"Sauerkräutler","weight":"1","pos":2004,"context":"...wird ein solches hiemit jedermann , wer etwann diesen <mark>Sauerkräutler<\/mark> = handel , samt Zugehörde , oder diese ","fid":"page"}]},{"docId":"ed__1745-10-20","docUri":"ed__1745-10-20.html","score":1,"contexts":[{"form":"Sauerkräutl","weight":"1","pos":2374,"context":"...alt 48. J. Dem Jos. Wildgans, Burgerl. <mark>Sauerkräutl<\/mark>., s. K. Jos., im Holleins. H. im...","fid":"page"}]},{"docId":"ed__1771-03-16","docUri":"ed__1771-03-16.html","score":1,"contexts":[{"form":"Sauerkräutl","weight":"1","pos":1612,"context":".... Reitkn . s . K . Johann im <mark>Sauerkräutl<\/mark> . H . in der Alsterg . alt 7...","fid":"page"}]},{"docId":"ed__1783-06-21","docUri":"ed__1783-06-21.html","score":1,"contexts":[{"form":"Sauerkräutlers","weight":"1","pos":2953,"context":"..., eines Kleinuhrmachers , eines Grattelträgers , und eines <mark>Sauerkräutlers<\/mark> gegen die nachfolgenden Bedingnisse zu verkau= fen ;...","fid":"page"}]},{"docId":"ed__1779-05-29","docUri":"ed__1779-05-29.html","score":1,"contexts":[{"form":"Sauerkräutl","weight":"1","pos":1648,"context":" Jos . Rückermann , <mark>Sauerkräutl<\/mark> . Nr . 22 . auff . Ma= riahilf...","fid":"page"}]},{"docId":"ed__1793-02-02","docUri":"ed__1793-02-02.html","score":1,"contexts":[{"form":"Sauerkräutlers","weight":"1","pos":4852,"context":"...Hauses Nr. 43 in der Alstergasse, worauf ein <mark>Sauerkräutlers<\/mark>=gewerb radiziret, und von einem neu gebau...","fid":"page"}]},{"docId":"ed__1796-06-15","docUri":"ed__1796-06-15.html","score":1,"contexts":[{"form":"Sauerkräutl","weight":"1","pos":2056,"context":".... Joh . Mich . Halmschlöger , bg . <mark>Sauerkräutl<\/mark> . alt 69 J . in s . H...","fid":"page"}]},{"docId":"ed__1798-09-29","docUri":"ed__1798-09-29.html","score":1,"contexts":[{"form":"Sauerkräutler","weight":"1","pos":2091,"context":"...J. am Neustift N. 14. Dem Jos. Schneider. <mark>Sauerkräutler<\/mark>, s. K. Franz, alt 6 J auf...","fid":"page"}]}]}