{"stem":"seiler","instances":[{"docId":"ed__1725-05-09","docUri":"ed__1725-05-09.html","score":1,"contexts":[{"form":"Seiler","weight":"1","pos":1758,"context":" Dem Adam Claus \/ <mark>Seiler<\/mark> \/ s. K. Anna beym roten Kreb=sen am...","fid":"page"}]},{"docId":"ed__1771-03-09","docUri":"ed__1771-03-09.html","score":1,"contexts":[{"form":"Seiler","weight":"1","pos":4826,"context":"...ge= denken , sich in dem Jacoberhaus auf der <mark>Seiler<\/mark>= stadt im ersten Stock an obernannten Tag von...","fid":"page"}]},{"docId":"ed__1741-03-15","docUri":"ed__1741-03-15.html","score":1,"contexts":[{"form":"Seiler","weight":"1","pos":1704,"context":"...W. Elisabeth \/ im Körberis. H. auf der <mark>Seiler<\/mark>=stadt \/ alt 25. J. Dem Joseph Bachinger...","fid":"page"}]},{"docId":"ed__1786-03-11","docUri":"ed__1786-03-11.html","score":1,"contexts":[{"form":"Seiler","weight":"1","pos":3751,"context":".... Babitsch, zur Fama genannt, in der <mark>Seiler<\/mark>=gasse (Krautgässel) dem Matschackerhofe über, sind...","fid":"page"}]},{"docId":"ed__1727-11-12","docUri":"ed__1727-11-12.html","score":1,"contexts":[{"form":"Seiler","weight":"1","pos":2230,"context":"...Vor der Stadt . Dem Joh . Bapt . <mark>Seiler<\/mark> \/ B . Cafee = Siedern \/ s ....","fid":"page"}]},{"docId":"ed__1734-07-24","docUri":"ed__1734-07-24.html","score":1,"contexts":[{"form":"Seiler","weight":"1","pos":1674,"context":"...Ca= spar \/ in ihrem h . auf der <mark>Seiler<\/mark> = statt \/ alt 21 . J . Vor...","fid":"page"}]},{"docId":"ed__1720-01-20","docUri":"ed__1720-01-20.html","score":1,"contexts":[{"form":"Seiler","weight":"1","pos":1526,"context":"...\/ d Custodr , R . P . Wolfgango <mark>Seiler<\/mark> \/ 113 . Aloysio ","fid":"page"}]},{"docId":"ed__1722-01-03","docUri":"ed__1722-01-03.html","score":1,"contexts":[{"form":"Seiler","weight":"1","pos":1606,"context":"...ihr S. Joseph Frantz Antoni. Dem Johann Georg <mark>Seiler<\/mark> \/ und Maria Anna sein Ehew. ihr S....","fid":"page"}]},{"docId":"ed__1719-07-01","docUri":"ed__1719-07-01.html","score":1,"contexts":[{"form":"Seiler","weight":"1","pos":1347,"context":"...Soldat \/ im Quartier=Häußel \/ auf der <mark>Seiler<\/mark>=statt \/ alt 36. Jahr. Vor ","fid":"page"}]},{"docId":"ed__1747-01-07","docUri":"ed__1747-01-07.html","score":1,"contexts":[{"form":"Seiler","weight":"1","pos":1957,"context":".... Wittwe , in ihrem H . auf der <mark>Seiler<\/mark> = stadt , alt 70 . J . Vor...","fid":"page"}]},{"docId":"ed__1730-03-25","docUri":"ed__1730-03-25.html","score":1,"contexts":[{"form":"Seiler","weight":"1","pos":1857,"context":"...Liechtenthal \/ alt 28 . J . Dem Leopold <mark>Seiler<\/mark> \/ armen Mann \/ s . K . Anna...","fid":"page"}]},{"docId":"ed__1732-02-13","docUri":"ed__1732-02-13.html","score":1,"contexts":[{"form":"Seiler","weight":"1","pos":1589,"context":"...Marx Melau \/ Portier in dem Althannischen Haus im <mark>Seiler<\/mark>=Gässel \/ allda \/ alt 45. J. Vor...","fid":"page"}]}]}