{"stem":"sidenten","instances":[{"docId":"ed__1791-12-10","docUri":"ed__1791-12-10.html","score":2,"contexts":[{"form":"sidenten","weight":"1","pos":300,"context":"...erledigte Gu= bernium von Steyermark , an den Prä= <mark>sidenten<\/mark> und Landeshauptmann von Kärn= ten , Grafen v...","fid":"p15"},{"form":"sidenten","weight":"1","pos":316,"context":"...Hofkanzley , Grafen v . Odonell , zum Prä= <mark>sidenten<\/mark> und Landeshauptmann in Kärn= ten ernannt , des...","fid":"p15"}]},{"docId":"ed__1795-06-27","docUri":"ed__1795-06-27.html","score":1,"contexts":[{"form":"sidenten","weight":"1","pos":1343,"context":"...die beyden Ge= sandten einen Etikettebesuch bey dem Prä= <mark>sidenten<\/mark> der Konvenz. und bey dem Vorsitzer des Wohlfahrts...","fid":"p53"}]},{"docId":"ed__1732-05-31","docUri":"ed__1732-05-31.html","score":1,"contexts":[{"form":"sidenten","weight":"1","pos":1244,"context":"...heimen Raht \/ Hof=Cammer=Vice-Præ- <mark>sidenten<\/mark> \/ ꝛc. und (Tit.) Hrn. Berthol- dum Abten...","fid":"p28"}]},{"docId":"ed__1741-03-15","docUri":"ed__1741-03-15.html","score":1,"contexts":[{"form":"sidenten","weight":"1","pos":251,"context":"...bey der Garde \/ Woyekoff; Zu Vice=Præ= <mark>sidenten<\/mark> in denen Collegiis \/ und zwar in der Revisions...","fid":"p5"}]},{"docId":"ed__1732-07-09","docUri":"ed__1732-07-09.html","score":1,"contexts":[{"form":"sidenten","weight":"1","pos":1254,"context":"...Ehrenberg \/ Dienst in Dantzig bey dem Schwedischen Re= <mark>sidenten<\/mark> 363. an der Zahl erhalten \/ wel= che Berg...","fid":"p29"}]},{"docId":"ed__1710-09-10","docUri":"ed__1710-09-10.html","score":1,"contexts":[{"form":"sidenten","weight":"1","pos":197,"context":"...Kayserl . Herrn Vice = Kriegs = Præ = <mark>sidenten<\/mark> \/ Grafen von Herberstein \/ ꝛc . und des...","fid":"p9"}]},{"docId":"ed__1747-02-01","docUri":"ed__1747-02-01.html","score":1,"contexts":[{"form":"sidenten","weight":"1","pos":200,"context":"...Commercien = Gericht alle Beamte bis auf dem Prä= <mark>sidenten<\/mark> und 5 . Rähte als überflüssige Personen abgedankt worden...","fid":"p10"}]},{"docId":"ed__1768-03-05","docUri":"ed__1768-03-05.html","score":1,"contexts":[{"form":"sidenten","weight":"1","pos":13,"context":"...an ihrem Hofe be= findlichen königlich=pohlnischen Re= <mark>sidenten<\/mark>, Herrn Pfarsky, überreichte pro Memoria den 28....","fid":"p4"}]},{"docId":"ed__1789-09-16","docUri":"ed__1789-09-16.html","score":1,"contexts":[{"form":"sidenten","weight":"1","pos":278,"context":"...der Feyerlichkeit an= gemessene Reden an den neuen Prä= <mark>sidenten<\/mark>, der sie mit der ihm eige= nen...","fid":"p28"}]},{"docId":"ed__1783-12-24","docUri":"ed__1783-12-24.html","score":1,"contexts":[{"form":"sidenten","weight":"1","pos":1190,"context":"...) Sir Henry Fletscher , ( den bisgerigen Prä= <mark>sidenten<\/mark> der gegenwärtigen Compagnie Direktion ) 7 ) Hrn ....","fid":"p28"}]},{"docId":"ed__1771-03-23","docUri":"ed__1771-03-23.html","score":1,"contexts":[{"form":"sidenten","weight":"1","pos":371,"context":"...Abten Hoc= quart , einen Anverwandten von einem Prä= <mark>sidenten<\/mark> bey gedachten Parlamente , der sich durch seinen patriotischen...","fid":"p16"}]},{"docId":"ed__1777-08-02","docUri":"ed__1777-08-02.html","score":1,"contexts":[{"form":"sidenten","weight":"1","pos":766,"context":"...von unserm Ma= gistrat noch von dem französischen Re= <mark>sidenten<\/mark> die Besuche angenommen . Am 14 . des Morgens...","fid":"p34"}]},{"docId":"ed__1703-11-19","docUri":"ed__1703-11-19.html","score":1,"contexts":[{"form":"sidenten","weight":"1","pos":1422,"context":"...Röm. Käyserl. Mas. Cammerern und gewesten verordneten Præ= <mark>sidenten<\/mark> in Ober=Oesterreich \/ höchst=seeligen Angedenckens...","fid":"p25"}]},{"docId":"ed__1792-03-10","docUri":"ed__1792-03-10.html","score":1,"contexts":[{"form":"sidenten","weight":"1","pos":1256,"context":"...habe . Hierüber würde beschlossen , durch den Prä= <mark>sidenten<\/mark> den Unterofficieren und Soldaten des Regiments Soissonnois das Wohlge...","fid":"p49"}]},{"docId":"ed__1751-12-11","docUri":"ed__1751-12-11.html","score":1,"contexts":[{"form":"sidenten","weight":"1","pos":378,"context":"...haben letzteren Sonntag dem ersten Präsidenten , einem Prä= <mark>sidenten<\/mark> a Mortier , und einigen anderen Glie= deren...","fid":"p10"}]}]}