{"stem":"stetner","instances":[{"docId":"ed__1761-11-25","docUri":"ed__1761-11-25.html","score":1,"contexts":[{"form":"Stetner","weight":"1","pos":1622,"context":"...ewige Stillschweigen auferleget werden solle . Gabriel Joseph von <mark>Stetner<\/mark> Landschreiber . Franz Bernhard Edler v . Keeß ,...","fid":"p58"}]},{"docId":"ed__1728-08-04","docUri":"ed__1728-08-04.html","score":1,"contexts":[{"form":"Stetner","weight":"1","pos":1879,"context":" Dem Joh . <mark>Stetner<\/mark> \/ Lackeyen \/ s . K . Anton \/...","fid":"i42"}]}]}