{"stem":"verschrei","instances":[{"docId":"ed__1776-12-18","docUri":"ed__1776-12-18.html","score":1,"contexts":[{"form":"verschrei","weight":"1","pos":2515,"context":"...und Szawel bis zu ih= rer gänzlichen Bezahlung zu <mark>verschrei<\/mark>= ben , und das auf das feyerlichste für...","fid":"p126"}]},{"docId":"ed__1726-09-07","docUri":"ed__1726-09-07.html","score":1,"contexts":[{"form":"Verschrei","weight":"1","pos":496,"context":" nes , Wechsel = Brief \/ Reverses , <mark>Verschrei<\/mark>= bungen \/ oder Schulden für einländische \/ und...","fid":"p15"}]},{"docId":"ed__1754-08-14","docUri":"ed__1754-08-14.html","score":1,"contexts":[{"form":"Verschrei","weight":"1","pos":1655,"context":"...darauf ohnehin ausser allem rechtlichen Effect gestellten Obligationen, <mark>Verschrei<\/mark>= bungen und Ceßionen ꝛc. auf das sorgfäl=...","fid":"p37"}]},{"docId":"ed__1793-10-30","docUri":"ed__1793-10-30.html","score":1,"contexts":[{"form":"Verschrei","weight":"1","pos":2501,"context":"...freywillig erklärt und verpflichtet habe, keine weitere Schulden oder <mark>Verschrei<\/mark>= bungen, unter was immer für einen Namen...","fid":"p72"}]}]}