{"stem":"wohledl","instances":[{"docId":"ed__1780-12-13","docUri":"ed__1780-12-13.html","score":2,"contexts":[{"form":"wohledl","weight":"1","pos":1810,"context":"Dem <mark>wohledl<\/mark>. Hrn. Joh. 〈…〉zicka, k. k. böhm...","fid":"p61"},{"form":"wohledle","weight":"1","pos":1970,"context":"Der <mark>wohledle<\/mark> Hr. Adam Schaller, k. k. Reg. Kan= zelist...","fid":"p95"}]},{"docId":"ed__1766-04-09","docUri":"ed__1766-04-09.html","score":2,"contexts":[{"form":"Wohledle","weight":"1","pos":1939,"context":" Der <mark>Wohledle<\/mark> Hr . Barthol . Habit , Gmnr . Stadt...","fid":"i18"},{"form":"Wohledl","weight":"1","pos":1950,"context":" Dem <mark>Wohledl<\/mark> . Hrn . Math . Zohl , K ....","fid":"i19"}]},{"docId":"ed__1766-04-12","docUri":"ed__1766-04-12.html","score":2,"contexts":[{"form":"Wohledl","weight":"1","pos":1630,"context":" Dem <mark>Wohledl<\/mark> . Hrn . Joh . Georg Reiß , K...","fid":"i17"},{"form":"Wohledl","weight":"1","pos":1694,"context":" Dem <mark>Wohledl<\/mark> . Hrn . Nic . Appl , K ....","fid":"i27"}]},{"docId":"ed__1777-05-28","docUri":"ed__1777-05-28.html","score":2,"contexts":[{"form":"wohledle","weight":"1","pos":1580,"context":" Der <mark>wohledle<\/mark> Hr . Franz Jos . Bargehr , gew ....","fid":"i46"},{"form":"wohledle","weight":"1","pos":1673,"context":" Der <mark>wohledle<\/mark> Hr . Joh . Georg Höglmüller , k ....","fid":"i63"}]},{"docId":"ed__1781-10-17","docUri":"ed__1781-10-17.html","score":2,"contexts":[{"form":"wohledl","weight":"1","pos":1688,"context":" Der <mark>wohledl<\/mark> . Fr . Barb . Nonnerin , k ....","fid":"i2"},{"form":"wohledle","weight":"1","pos":1800,"context":" Der <mark>wohledle<\/mark> Hr . Jos . Pichlmayer , k . k...","fid":"i23"}]},{"docId":"ed__1773-11-17","docUri":"ed__1773-11-17.html","score":2,"contexts":[{"form":"wohledle","weight":"1","pos":1821,"context":"Der <mark>wohledle<\/mark> Hr. Ant. Ziegler, weil. Jhro Maj. der Kaiserin...","fid":"i2"},{"form":"wohledl","weight":"1","pos":2038,"context":"Dem <mark>wohledl<\/mark>. Hrn. Lorenz Weyß, k. k. Oberbereut....","fid":"i45"}]},{"docId":"ed__1773-06-09","docUri":"ed__1773-06-09.html","score":1,"contexts":[{"form":"wohledle","weight":"1","pos":1836,"context":"Der <mark>wohledle<\/mark> Hr. Joh. Karl Riedl, k. k. Hofkam=...","fid":"i3"}]},{"docId":"ed__1772-06-24","docUri":"ed__1772-06-24.html","score":1,"contexts":[{"form":"wohledle","weight":"1","pos":1807,"context":"Der <mark>wohledle<\/mark> Hr. Christ. Gruber, k. k. Forstmeist....","fid":"i27"}]},{"docId":"ed__1781-12-12","docUri":"ed__1781-12-12.html","score":1,"contexts":[{"form":"wohledle","weight":"1","pos":1881,"context":" Der <mark>wohledle<\/mark> Hr . Joh . Kasp . Heinl , k...","fid":"i22"}]},{"docId":"ed__1771-03-16","docUri":"ed__1771-03-16.html","score":1,"contexts":[{"form":"Wohledle","weight":"1","pos":1484,"context":" Der <mark>Wohledle<\/mark> Hr . Franz Lang , k . k ....","fid":"i3"}]},{"docId":"ed__1771-03-20","docUri":"ed__1771-03-20.html","score":1,"contexts":[{"form":"Wohledle","weight":"1","pos":1265,"context":" Die <mark>Wohledle<\/mark> Frau M . Anna Fuchsin , k k ....","fid":"i27"}]},{"docId":"ed__1771-03-09","docUri":"ed__1771-03-09.html","score":1,"contexts":[{"form":"wohledle","weight":"1","pos":1395,"context":" Der <mark>wohledle<\/mark> Hr . Franz Ant . Wimmer , k ....","fid":"i2"}]},{"docId":"ed__1783-06-21","docUri":"ed__1783-06-21.html","score":1,"contexts":[{"form":"wohledl","weight":"1","pos":1785,"context":" Dem <mark>wohledl<\/mark> . Hrn . Franz Wenzl Götzl , k ....","fid":"i2"}]},{"docId":"ed__1783-09-10","docUri":"ed__1783-09-10.html","score":1,"contexts":[{"form":"wohledl","weight":"1","pos":2062,"context":" Dem <mark>wohledl<\/mark> . Hrn . Ant . Roßi , d ....","fid":"i58"}]},{"docId":"ed__1775-03-18","docUri":"ed__1775-03-18.html","score":1,"contexts":[{"form":"wohledle","weight":"1","pos":1595,"context":"Der <mark>wohledle<\/mark> Hr. Anton Declaire, k k. Kuchel= inspekt...","fid":"p79"}]},{"docId":"ed__1781-12-19","docUri":"ed__1781-12-19.html","score":1,"contexts":[{"form":"wohledl","weight":"1","pos":1811,"context":" Der <mark>wohledl<\/mark> . Hr . Joh Bapt . Hertzur , k...","fid":"i48"}]},{"docId":"ed__1772-05-20","docUri":"ed__1772-05-20.html","score":1,"contexts":[{"form":"wohledle","weight":"1","pos":1857,"context":"Der <mark>wohledle<\/mark> Hr. Seb. Lana, g⟨m⟩r. Stadt Wien Banco=...","fid":"i90"}]},{"docId":"ed__1781-12-22","docUri":"ed__1781-12-22.html","score":1,"contexts":[{"form":"wohledl","weight":"1","pos":1607,"context":" Der <mark>wohledl<\/mark> . Hr . Jgnatz Beer , Gmr . Stadt...","fid":"i2"}]},{"docId":"ed__1771-03-23","docUri":"ed__1771-03-23.html","score":1,"contexts":[{"form":"Wohledl","weight":"1","pos":1713,"context":" Der <mark>Wohledl<\/mark> . Fr . Josepha Crusin , k . k...","fid":"i3"}]},{"docId":"ed__1775-06-24","docUri":"ed__1775-06-24.html","score":1,"contexts":[{"form":"wohledle","weight":"1","pos":1821,"context":"Der <mark>wohledle<\/mark> Hr. Jgnaz Balthasar Desebruch. in s. H. Nr....","fid":"p122"}]},{"docId":"ed__1775-07-01","docUri":"ed__1775-07-01.html","score":1,"contexts":[{"form":"wohledle","weight":"1","pos":1525,"context":"Der <mark>wohledle<\/mark> Hr. Wenzel Jos. Kahl, jubil. k. k....","fid":"p66"}]},{"docId":"ed__1766-04-05","docUri":"ed__1766-04-05.html","score":1,"contexts":[{"form":"Wohledle","weight":"1","pos":2100,"context":" Die <mark>Wohledle<\/mark> Fr . Elis . Vlachin , Wittwe , im...","fid":"i32"}]},{"docId":"ed__1773-11-13","docUri":"ed__1773-11-13.html","score":1,"contexts":[{"form":"wohledl","weight":"1","pos":1797,"context":"Dem <mark>wohledl<\/mark>. Hrn. Joh. Conrad Steinebach, k. k. Hoflammer...","fid":"i21"}]},{"docId":"ed__1776-08-21","docUri":"ed__1776-08-21.html","score":1,"contexts":[{"form":"wohledle","weight":"1","pos":1481,"context":" Die <mark>wohledle<\/mark> Fr . Rosina Ludovica Krausin , k . k...","fid":"i2"}]}]}